{
	"ImportPath": "github.com/yudai/gojsondiff",
	"GoVersion": "go1.4",
	"Packages": [
		"./..."
	],
	"Deps": [
		{
			"ImportPath": "github.com/codegangsta/cli",
			"Comment": "1.2.0-95-g9b2bd2b",
			"Rev": "9b2bd2b3489748d4d0a204fa4eb2ee9e89e0ebc6"
		},
		{
			"ImportPath": "github.com/k0kubun/pp",
			"Comment": "v2.0.1-1-ge14f383",
			"Rev": "e14f383ae6cec46144a99394c284d3edb0970e65"
		},
		{
			"ImportPath": "github.com/mattn/go-colorable",
			"Rev": "d67e0b7d1797975196499f79bcc322c08b9f218b"
		},
		{
			"ImportPath": "github.com/onsi/ginkgo",
			"Comment": "v1.1.0-41-g38caab9",
			"Rev": "38caab951a9ff39f0e61294a1dbaaa074a39228b"
		},
		{
			"ImportPath": "github.com/onsi/gomega",
			"Comment": "v1.0-35-g4dfabf7",
			"Rev": "4dfabf7db2e4147ec99a86db32b2f2a3484cfee8"
		}
	]
}
